pyappauto/__init__.py
pyappauto/utils/errors.py
pyappauto/utils/keys.py
pyappauto-1.0.2.dist-info/LICENSE.txt
pyappauto-1.0.2.dist-info/METADATA
pyappauto-1.0.2.dist-info/WHEEL
pyappauto-1.0.2.dist-info/top_level.txt
pyappauto-1.0.2.dist-info/RECORD
