Metadata-Version: 2.1
Name: pyappauto
Version: 1.0.2
Summary: Control an app without disturbing your everyday life.
Home-page: https://github.com/User00092/PyAppAuto
Author: User0092
Author-email: unknownuser0092@protonmail.com
License: MIT
Keywords: Windows App control,App controller,PyAppAuto
Classifier: Development Status :: 5 - Production/Stable
Classifier: Topic :: Utilities
Classifier: Operating System :: Microsoft :: Windows
Classifier: Programming Language :: Python
Classifier: Intended Audience :: Developers
Requires-Python: >=3.7.0
License-File: LICENSE.txt
Requires-Dist: pywin32 (==306)
Requires-Dist: opencv-python (==4.7.0.72)
Requires-Dist: pygetwindow (==0.0.9)
Requires-Dist: numpy (==1.24.3)
